pyblocktext/__init__.py
pyblocktext-1.6.2.dist-info/LICENSE
pyblocktext-1.6.2.dist-info/METADATA
pyblocktext-1.6.2.dist-info/WHEEL
pyblocktext-1.6.2.dist-info/top_level.txt
pyblocktext-1.6.2.dist-info/RECORD
