Metadata-Version: 2.1
Name: pyblocktext
Version: 1.6.2
Summary: a python package to generate blocktext
Home-page: https://github.com/gubareve/py-blocktext/
Author: Evan Gubarev
Author-email: evan@evangubarev.com
License: MIT
Platform: UNKNOWN
Requires-Dist: numpy
